deezer_downloader/cli/deezer-downloader.ini.template
deezer_downloader/cli/runner.py
deezer_downloader/configuration.py
deezer_downloader/deezer.py
deezer_downloader/spotify.py
deezer_downloader/threadpool_queue.py
deezer_downloader/web/app.py
deezer_downloader/web/music_backend.py
deezer_downloader/web/static/css/bootstrap-4.1.3-dist.zip
deezer_downloader/web/static/css/bootstrap.bundle.min.js
deezer_downloader/web/static/css/bootstrap.min.css
deezer_downloader/web/static/css/custom.css
deezer_downloader/web/static/css/font-awesome.min.css
deezer_downloader/web/static/css/jquery.jgrowl.min.css
deezer_downloader/web/static/favicon.ico
deezer_downloader/web/static/fonts/fontawesome-webfont.woff2
deezer_downloader/web/static/js/bootstrap.min.js
deezer_downloader/web/static/js/custom.js
deezer_downloader/web/static/js/jquery.jgrowl.min.js
deezer_downloader/web/static/js/jquery.min.js
deezer_downloader/web/static/js/popper.min.js
deezer_downloader/web/templates/autoindex.html
deezer_downloader/web/templates/index.html
deezer_downloader/youtubedl.py
deezer_downloader-2.11.0.dist-info/METADATA
deezer_downloader-2.11.0.dist-info/WHEEL
deezer_downloader-2.11.0.dist-info/entry_points.txt
deezer_downloader-2.11.0.dist-info/licenses/LICENSE
deezer_downloader-2.11.0.dist-info/RECORD
