Metadata-Version: 2.4
Name: deezer-downloader
Version: 2.11.0
Summary: download music from Deezer with a nice front end
License-File: LICENSE
Author: kmille
Author-email: github@androidloves.me
Requires-Python: >=3.9.1,<4.0.0
Classifier: Programming Language :: Python :: 3
Classifier: Programming Language :: Python :: 3.10
Classifier: Programming Language :: Python :: 3.11
Classifier: Programming Language :: Python :: 3.12
Classifier: Programming Language :: Python :: 3.13
Classifier: Programming Language :: Python :: 3.14
Requires-Dist: flask (>=3.0.3,<4.0.0)
Requires-Dist: flask-autoindex (>=0.6.6,<0.7.0)
Requires-Dist: giphypop (>=0.3,<0.4)
Requires-Dist: jinja2 (>=3.1.2,<4.0.0)
Requires-Dist: mutagen (>=1.47.0,<2.0.0)
Requires-Dist: pycryptodome (>=3.16.0,<4.0.0)
Requires-Dist: pyotp (>=2.9.0,<3.0.0)
Requires-Dist: python-mpd2 (>=3.0.5,<4.0.0)
Requires-Dist: requests[socks] (>=2.28.2,<3.0.0)
Requires-Dist: waitress (>=3.0.0,<4.0.0)
Requires-Dist: yt-dlp
Project-URL: Homepage, https://github.com/kmille/deezer-downloader
Project-URL: Repository, https://github.com/kmille/deezer-downloader
